README
setup.py
tesolib/__init__.py
tesolib/tesolib.py
tesolib.egg-info/PKG-INFO
tesolib.egg-info/SOURCES.txt
tesolib.egg-info/dependency_links.txt
tesolib.egg-info/top_level.txt
tesolib/tests/__init__.py
tesolib/tests/test_teso.py