Metadata-Version: 1.1
Name: tesolib
Version: 0.0.4
Summary: Test script for publish packages in PIPY
Home-page: http://packages.python.org/tesolib
Author: Tesodev
Author-email: kenan.kurt@tesodev.com
License: BSD
Keywords: tesodev,tesolib
Platform: UNKNOWN
Classifier: Development Status :: 1 - Planning
Classifier: Topic :: Utilities
Classifier: License :: OSI Approved :: BSD License
